ua_clarity_tools/__init__.py
ua_clarity_tools/api_types.py
ua_clarity_tools/batch_artifact_update_template.xml
ua_clarity_tools/docs/ua_clarity_tools.html
ua_clarity_tools/routing_template.xml
ua_clarity_tools/tests/post_container_template.xml
ua_clarity_tools/tests/post_project_template.xml
ua_clarity_tools/tests/post_route_unroute_template.xml
ua_clarity_tools/tests/post_samples_batch_template.xml
ua_clarity_tools/tests/post_samples_template.xml
ua_clarity_tools/tests/test_ua_clarity_tools.py
ua_clarity_tools/ua_clarity_tools.py
ua_clarity_tools-1.1.9.dist-info/LICENSE
ua_clarity_tools-1.1.9.dist-info/METADATA
ua_clarity_tools-1.1.9.dist-info/WHEEL
ua_clarity_tools-1.1.9.dist-info/RECORD
