Metadata-Version: 2.1
Name: ua-clarity-tools
Version: 1.1.9
Summary: 
Author: Your Name
Author-email: you@example.com
Requires-Python: >=3.12,<4.0
Classifier: Programming Language :: Python :: 3
Classifier: Programming Language :: Python :: 3.12
Requires-Dist: beautifulsoup4 (>=4.12.3,<5.0.0)
Requires-Dist: jinja2 (>=3.1.4,<4.0.0)
Requires-Dist: requests (>=2.32.3,<3.0.0)
Requires-Dist: ua-clarity-api (>=1.1.6,<2.0.0)
